wok/__init__.py
wok/__main__.py
wok/cli.py
wok/config/__init__.py
wok/config/base.py
wok/config/schema.py
wok/core/__init__.py
wok/core/base.py
wok/core/cmd.py
wok/core/context.py
wok-0.1.0.dev1.dist-info/entry_points.txt
wok-0.1.0.dev1.dist-info/LICENSE
wok-0.1.0.dev1.dist-info/WHEEL
wok-0.1.0.dev1.dist-info/METADATA
wok-0.1.0.dev1.dist-info/RECORD
